pytest_warnings/__init__.py
pytest_warnings-0.3.1.dist-info/METADATA
pytest_warnings-0.3.1.dist-info/RECORD
pytest_warnings-0.3.1.dist-info/WHEEL
pytest_warnings-0.3.1.dist-info/entry_points.txt
pytest_warnings-0.3.1.dist-info/top_level.txt
