Metadata-Version: 1.1
Name: pytest-warnings
Version: 0.3.1
Summary: pytest plugin to list Python warnings in pytest report
Home-page: https://github.com/fschulze/pytest-warnings
Author: Florian Schulze
Author-email: florian.schulze@gmx.net
License: MIT license
Platform: UNKNOWN
Classifier: Framework :: Pytest
Classifier: Programming Language :: Python :: 2.7
Classifier: Programming Language :: Python :: 3.3
Classifier: Programming Language :: Python :: 3.4
Classifier: Programming Language :: Python :: 3.5
Classifier: Programming Language :: Python :: 3.6
Classifier: Development Status :: 7 - Inactive
